{
    "configurations": [
        {
            "name": "Linux",
            "includePath": [
                "${workspaceFolder}/**",
                "/usr/include/python3.12",
                "/usr/lib/python3/dist-packages/pybind11/include",
                "/home/zwouklebleu/Documents/STAGES/T1/Stage-A25-Zakary/extern"
            ],
            "defines": [],
            "compilerPath": "/usr/bin/gcc",
            "cStandard": "c17",
            "cppStandard": "gnu++20",
            "intelliSenseMode": "linux-gcc-x64"
        }
    ],
    "version": 4
}